[
  {
    "num": 1,
    "shapes": [
      {
        "idx": 0,
        "type": "GROUP (6)"
      },
      {
        "idx": 1,
        "type": "FREEFORM (5)"
      },
      {
        "idx": 2,
        "type": "FREEFORM (5)"
      }
    ]
  },
  {
    "num": 2,
    "shapes": [
      {
        "idx": 0,
        "type": "FREEFORM (5)"
      },
      {
        "idx": 1,
        "type": "FREEFORM (5)"
      },
      {
        "idx": 2,
        "type": "TEXT_BOX (17)",
        "text": "Егор Иванов"
      },
      {
        "idx": 3,
        "type": "TEXT_BOX (17)",
        "text": "Выпускник New York Film Academy, бывший документалист, а теперь — режиссер рекламы и бренд-контента, который одинаково вдохновляется няшными детишками, контактными видами спорта и рёвом тяжелой техники."
      },
      {
        "idx": 4,
        "type": "TEXT_BOX (17)",
        "text": "Режиссер постановщик (KZ)"
      },
      {
        "idx": 5,
        "type": "FREEFORM (5)"
      },
      {
        "idx": 6,
        "type": "GROUP (6)"
      }
    ]
  },
  {
    "num": 3,
    "shapes": [
      {
        "idx": 0,
        "type": "MEDIA (16)",
        "media": true
      }
    ]
  },
  {
    "num": 4,
    "shapes": [
      {
        "idx": 0,
        "type": "FREEFORM (5)"
      },
      {
        "idx": 1,
        "type": "FREEFORM (5)"
      },
      {
        "idx": 2,
        "type": "GROUP (6)"
      },
      {
        "idx": 3,
        "type": "FREEFORM (5)"
      },
      {
        "idx": 4,
        "type": "TEXT_BOX (17)",
        "text": "Павел Янкевич"
      },
      {
        "idx": 5,
        "type": "TEXT_BOX (17)",
        "text": "Путь Паши в кино начался в ГИТРе (Москва), где он пять лет осваивал операторское мастерство, параллельно набираясь практического опыта, ассистируя на съемках короткометражек во ВГИКе, ГИТРе, Московской школе кино и на других студенческих и независимых площадках."
      },
      {
        "idx": 6,
        "type": "TEXT_BOX (17)",
        "text": "Оператор постановщик (KZ)"
      }
    ]
  },
  {
    "num": 5,
    "shapes": [
      {
        "idx": 0,
        "type": "MEDIA (16)",
        "media": true
      }
    ]
  },
  {
    "num": 6,
    "shapes": [
      {
        "idx": 0,
        "type": "FREEFORM (5)"
      },
      {
        "idx": 1,
        "type": "GROUP (6)"
      },
      {
        "idx": 2,
        "type": "FREEFORM (5)"
      },
      {
        "idx": 3,
        "type": "FREEFORM (5)"
      },
      {
        "idx": 4,
        "type": "TEXT_BOX (17)",
        "text": "Тео Госеллин"
      },
      {
        "idx": 5,
        "type": "TEXT_BOX (17)",
        "text": "Тео — фотограф из Парижа, Франция, работающий на высоком международном уровне. Его стиль отличается тонким чувством света, композиции и современной визуальной эстетикой, благодаря чему он сотрудничает с брендами и креативными проектами в Европе."
      },
      {
        "idx": 6,
        "type": "TEXT_BOX (17)",
        "text": "Фотограф (FR)"
      }
    ]
  },
  {
    "num": 7,
    "shapes": [
      {
        "idx": 0,
        "type": "FREEFORM (5)"
      },
      {
        "idx": 1,
        "type": "FREEFORM (5)"
      }
    ]
  },
  {
    "num": 8,
    "shapes": [
      {
        "idx": 0,
        "type": "FREEFORM (5)"
      }
    ]
  },
  {
    "num": 9,
    "shapes": [
      {
        "idx": 0,
        "type": "FREEFORM (5)"
      },
      {
        "idx": 1,
        "type": "FREEFORM (5)"
      }
    ]
  }
]